dagster_apprise/__init__.py
dagster_apprise/_utils.py
dagster_apprise/components.py
dagster_apprise/hooks.py
dagster_apprise/resource.py
dagster_apprise-0.0.2.dist-info/METADATA
dagster_apprise-0.0.2.dist-info/WHEEL
dagster_apprise-0.0.2.dist-info/entry_points.txt
dagster_apprise-0.0.2.dist-info/top_level.txt
dagster_apprise-0.0.2.dist-info/RECORD
