Metadata-Version: 2.4
Name: dagster-apprise
Version: 0.0.2
Summary: Get notified when your Dagster runs succeed, fail, or change status across 70+ services including Slack, Discord, Pushover, Telegram, and more.
Requires-Python: >=3.10
Requires-Dist: dagster>=1.8.0
Requires-Dist: apprise>=1.6.0
Requires-Dist: pydantic>=2.6
